xmlparsing/__init__.py
xmlparsing/_main.py
xmlparsing-0.0.1.dist-info/METADATA
xmlparsing-0.0.1.dist-info/WHEEL
xmlparsing-0.0.1.dist-info/licenses/LICENSE
xmlparsing-0.0.1.dist-info/RECORD
