Metadata-Version: 2.1
Name: xmlparsing
Version: 0.0.1
Summary: Converts Python dictionaries to XML, JSON to XML, compiles XML, converts XML to JSON, and a lot more!
Project-URL: Homepage, https://github.com/Minetezter/xmlparsing
Project-URL: Bug Tracker, https://github.com/Minetezter/xmlparsing/issues
Author-email: Minetester <minetezter@protonmail.com>
License-File: LICENSE
Classifier: Intended Audience :: Developers
Classifier: License :: OSI Approved :: MIT License
Classifier: Operating System :: POSIX :: Linux
Classifier: Programming Language :: Python :: 3
Requires-Python: >=3.7
Requires-Dist: xml-to-dict>=0.1.6
Requires-Dist: xmlformatter>=0.2.4
